heniautos/__init__.py
heniautos/__main__.py
heniautos/__version__.py
heniautos/calendar_equation.py
heniautos/command_line.py
heniautos/ephemeris.py
heniautos/equations.py
heniautos/heniautos.py
heniautos/new_moons.tsv
heniautos/prytanies.py
heniautos/solstices.tsv
tests/__init__.py
tests/conftest.py
tests/test_calculations.py
tests/test_equations.py
tests/test_heniautos.py
tests/test_loading_data.py
tests/test_prytanies.py
heniautos-2.2.0.dist-info/LICENSE
heniautos-2.2.0.dist-info/METADATA
heniautos-2.2.0.dist-info/WHEEL
heniautos-2.2.0.dist-info/entry_points.txt
heniautos-2.2.0.dist-info/top_level.txt
heniautos-2.2.0.dist-info/RECORD
