Metadata-Version: 2.1
Name: heniautos
Version: 2.2.0
Summary: Ancient Athenian calendar generator
Home-page: https://github.com/seanredmond/heniautos
Author: Sean Redmond
Author-email: github-smr@sneakemail.com
Project-URL: Bug Tracker, https://github.com/seanredmond/heniautos/issues
Classifier: Programming Language :: Python :: 3
Classifier: License :: OSI Approved :: GNU General Public License v3 or later (GPLv3+)
Classifier: Operating System :: OS Independent
Requires-Python: >=3.8
License-File: LICENSE
Requires-Dist: juliandate
